mozrunner/__init__.py
mozrunner/application.py
mozrunner/cli.py
mozrunner/errors.py
mozrunner/runners.py
mozrunner/utils.py
mozrunner/base/__init__.py
mozrunner/base/browser.py
mozrunner/base/device.py
mozrunner/base/runner.py
mozrunner/devices/__init__.py
mozrunner/devices/android_device.py
mozrunner/devices/base.py
mozrunner/devices/emulator.py
mozrunner/devices/emulator_battery.py
mozrunner/devices/emulator_geo.py
mozrunner/devices/emulator_screen.py
mozrunner/devices/telnetlib.py
mozrunner-8.3.2.dist-info/METADATA
mozrunner-8.3.2.dist-info/WHEEL
mozrunner-8.3.2.dist-info/entry_points.txt
mozrunner-8.3.2.dist-info/top_level.txt
mozrunner-8.3.2.dist-info/RECORD
